{"cameraMode":{"drawMode":0,"name":"Shaded","section":"Shading Mode"},"sceneLighting":true,"audioPlay":false,"sceneViewState":{"m_AlwaysRefresh":false,"showFog":true,"showSkybox":true,"showFlares":true,"showImageEffects":true,"showParticleSystems":true,"showVisualEffectGraphs":true,"m_FxEnabled":true},"in2DMode":false,"pivot":{"x":11.227089881896973,"y":6.359274864196777,"z":44.66395568847656},"rotation":{"x":0.05464884266257286,"y":-0.18939445912837983,"z":0.011243361048400402,"w":0.9805441498756409},"size":1.9167368412017823,"orthographic":false}